<?xml version="1.0" encoding="UTF-8"?>
<WebForm _uuid="]0fLLvURFj4q9sJTidzhjA" name="game.editor.entity.GroupForm" label="M#12cn19设计-实体分组表单" is_valid="Y" note="M#" style_refer="design.ControlStyle" edit_insert="Y" edit_update="Y" action="/system/design/weblist/WebList.wa?type=list">
  <DataAction _uuid="m0mx1JB0EEYnIi89VtH4gg" name="insertAction" label="M#12cn14新建处理" is_valid="Y" note="M#" service="insert@game.editor.entity" />
  <DataAction _uuid="lE8nhAz4g3We]K0QlX25oQ" name="updateAction" label="M#12cn14保存处理" is_valid="Y" note="M#" service="update@game.editor.entity" />
  <DataAction _uuid="l0ov9yvZq]fhzATb0xgNoA" name="deleteAction" label="M#12cn14删除处理" is_valid="Y" note="M#" service="delete@game.editor.entity" />
  <DataAction _uuid="Akj2QAII8CTol8EHeL5iiA" name="sortAction" label="M#12cn14排序处理" is_valid="Y" note="M#" service="sort@game.editor.entity" />
  <ToolBar _uuid="uUfFGZoz9Z4AxffAp9nymA" name="toolBar" label="M#12cn13工具栏" is_valid="Y" note="M#" disp_search="Y" disp_picker="Y" disp_list="Y" disp_insert="Y" disp_update="Y" disp_delete="Y" width="100%" height="24">
    <ToolButton _uuid="vkWB3X[7cuprMsLgWiMbuA" name="saveButton" label="M#12cn12保存" is_valid="Y" note="M#" disp_search="Y" disp_picker="Y" disp_list="Y" disp_insert="Y" disp_update="Y" disp_delete="Y" icon="tool.save" icon_disable="tool.saves" hotkey="F8" action="doSave()" />
    <ToolButton _uuid="ZElcexwulPSOiAU9zaykoQ" name="deleteButton" label="M#12cn12删除" is_valid="Y" note="M#" disp_search="Y" disp_picker="Y" disp_list="Y" disp_update="Y" disp_delete="Y" icon="tool.delete" icon_disable="tool.deleted" hotkey="F6" action="doDelete()" />
    <ToolButtonSplit _uuid="lUY4WlhKpXwYW7lYaqG5tg" name="split1Button" label="M#12cn12分割" is_valid="Y" note="M#" disp_list="Y" disp_update="Y" disp_delete="Y" />
    <ToolButtonMenu _uuid="kUeAM9xDilMD]FKMmhZGoQ" name="insertButton" label="M#12cn12新建" is_valid="Y" note="M#" disp_search="Y" disp_picker="Y" disp_list="Y" disp_insert="Y" disp_update="Y" disp_delete="Y" icon="tool.insert">
      <MenuButton _uuid="MEhOFfPir4ZPVDEfPTQyjg" name="insertEntity" label="M#12cn14新建实体" is_valid="Y" note="M#" disp_list="Y" disp_insert="Y" disp_update="Y" disp_delete="Y" icon="game.editor.entity.entity" page="insert@#/editor/entity/Entity.wa" attributes="_type=Entity\nsel_type=component\nform_name=game.editor.entity.EntityForm" />
      <MenuButton _uuid="aU8kHg6ZMHcbhGvGdgS1tA" name="insertTemplate" label="M#12cn14新建模板" is_valid="Y" note="M#" disp_list="Y" disp_insert="Y" disp_update="Y" disp_delete="Y" icon="game.editor.entity.template" page="insert@#/editor/entity/Entity.wa" attributes="_type=EntityTemplate\nsel_type=component\nform_name=game.editor.entity.EntityTemplateForm" />
      <MenuButton _uuid="sU]csxMPSIhvm8KfJb[Dgw" name="insertStruct" label="M#12cn14新建结构" is_valid="Y" note="M#" disp_list="Y" disp_insert="Y" disp_update="Y" disp_delete="Y" icon="game.editor.entity.struct" page="insert@#/editor/entity/Entity.wa" attributes="_type=Struct\nsel_type=component\nform_name=game.editor.entity.StructForm" />
      <MenuButton _uuid="9UcyA[cmzVMAOXWhbmO0ug" name="insertType" label="M#12cn14新建类型" is_valid="Y" note="M#" disp_list="Y" disp_insert="Y" disp_update="Y" disp_delete="Y" icon="game.editor.entity.type" page="insert@#/editor/entity/Entity.wa" attributes="_type=Type\nsel_type=component\nform_name=game.editor.entity.TypeForm" />
    </ToolButtonMenu>
    <ToolButtonSplit _uuid="fE8fmkyXTGF4kMDAcgKFiw" name="split2Button" label="M#12cn12分割" is_valid="Y" note="M#" disp_list="Y" disp_update="Y" disp_delete="Y" />
    <ToolButton _uuid="V0g3S0p[Iv79ebjmz6uhlA" name="sortButton" label="M#12cn12排序" is_valid="Y" note="M#" disp_search="Y" disp_picker="Y" disp_list="Y" disp_update="Y" disp_delete="Y" icon="tool.design" icon_disable="tool.design" hotkey="F9" page="sort@#/editor/entity/Entity.wa" attributes="sel_type=collection" />
    <ToolButtonSplit _uuid="rUpsmwGX9flpcysEOuvepg" name="spiltbuild" label="M#12cn12分割" is_valid="Y" note="M#" disp_list="Y" disp_insert="Y" disp_update="Y" disp_delete="Y" />
    <ToolButtonMenu _uuid="j0dQCQ8jABkNp9b4JZcbqg" name="buildSource" label="M#12cn12代码" is_valid="Y" note="M#" disp_search="Y" disp_picker="Y" disp_list="Y" disp_insert="Y" disp_update="Y" disp_delete="Y">
      <MenuButton _uuid="pEtchljKPnaYDyiSdFXikw" name="buildSourceHead" label="M#12cn13头文件" is_valid="Y" note="M#" disp_list="Y" disp_insert="Y" disp_update="Y" disp_delete="Y" page="buildSource@#/editor/entity/Entity.wa?type=head" />
      <MenuButton _uuid="ckLYlJkqS5I0QTV[2xt6oQ" name="buildSourceBody" label="M#12cn13体文件" is_valid="Y" note="M#" disp_list="Y" disp_insert="Y" disp_update="Y" disp_delete="Y" page="buildSource@#/editor/entity/Entity.wa?type=body" />
    </ToolButtonMenu>
  </ToolBar>
  <Select _uuid="C0oTf7nlsQ[jd[o4S2tEmA" name="componentType" label="M#12cn14控件类型" is_valid="Y" note="M#" disp_search="Y" disp_picker="Y" disp_list="Y" disp_insert="Y" disp_update="Y" disp_delete="Y" nowrap="Y" style_edit="selectWide" data_name="_TYPE" data_default="Message" edit_zoom="N" valid_insert="Y" valid_update="Y" valid_delete="Y" valid_require="Y" edit_refer="game.editor.entity.ComponentType" edit_dynamic="N" />
  <Check _uuid="2kItZU7Cl2vYzX6E1rH7kg" name="isValid" label="M#12cn13有效性" is_valid="Y" note="M#" disp_search="Y" disp_picker="Y" disp_list="Y" disp_insert="Y" disp_update="Y" disp_delete="Y" data_name="IS_VALID" data_default="Y" edit_insert="Y" edit_update="Y" valid_insert="Y" valid_update="Y" />
  <Edit _uuid="4kjFMZsnZ1a5aYmMmVVZgg" name="name" label="M#12cn12名称" is_valid="Y" note="M#" disp_search="Y" disp_picker="Y" disp_list="Y" disp_insert="Y" disp_update="Y" disp_delete="Y" style_edit="editWide" data_name="NAME" edit_insert="Y" edit_delete="Y" edit_zoom="N" valid_insert="Y" valid_delete="Y" valid_require="Y" />
  <Edit _uuid="FkX]HGqCwBhzunk[FXyOtQ" name="label" label="M#12cn12标签" is_valid="Y" note="M#" disp_search="Y" disp_picker="Y" disp_list="Y" disp_insert="Y" disp_update="Y" disp_delete="Y" style_edit="editMax" data_name="LABEL" edit_insert="Y" edit_update="Y" edit_zoom="N" valid_insert="Y" valid_update="Y" valid_require="Y" />
  <Split _uuid="akhUp8K124VgMzDvV2HHpg" name="optionSplitter" label="M#12cn14设置信息" is_valid="Y" note="M#" disp_search="Y" disp_lov="Y" disp_display="Y" disp_insert="Y" disp_update="Y" disp_delete="Y" disp_print="Y" edit_extend="Y" />
  <Edit _uuid="J0xko9sndjCqRsiFa[QVjg" name="projectName" label="M#12cn14项目名称" is_valid="Y" note="M#" disp_search="Y" disp_lov="Y" disp_display="Y" disp_insert="Y" disp_update="Y" disp_delete="Y" disp_print="Y" style_refer="controlMax" style_edit="editMax" data_fetch="Y" data_name="PROJECT_NAME" edit_insert="Y" edit_update="Y" edit_zoom="N" edit_copy="Y" valid_insert="Y" valid_update="Y" />
  <Edit _uuid="mkSHNO8bS]4]kQ1dBLmxtw" name="projectCode" label="M#12cn14项目代码" is_valid="Y" note="M#" disp_search="Y" disp_lov="Y" disp_display="Y" disp_insert="Y" disp_update="Y" disp_delete="Y" disp_print="Y" style_edit="editWide" data_fetch="Y" data_name="PROJECT_CODE" edit_insert="Y" edit_update="Y" edit_zoom="N" edit_copy="Y" valid_insert="Y" valid_update="Y" />
  <Edit _uuid="EknBCbTTrJ2xtPuXnQeOsA" name="sourceName" label="M#12cn14代码名称" is_valid="Y" note="M#" disp_search="Y" disp_lov="Y" disp_display="Y" disp_insert="Y" disp_update="Y" disp_delete="Y" disp_print="Y" nowrap="Y" style_edit="editWide" data_name="SOURCE_NAME" edit_insert="Y" edit_update="Y" edit_zoom="N" edit_copy="Y" valid_insert="Y" valid_update="Y" valid_require="Y" edit_width="245" />
  <Number _uuid="KEUiUdqT6QGuhfbJUidImg" name="displayIndex" label="M#12cn14显示顺序" is_valid="Y" note="M#" disp_search="Y" disp_lov="Y" disp_display="Y" disp_insert="Y" disp_update="Y" disp_delete="Y" disp_print="Y" data_fetch="Y" data_name="DISPLAY_INDEX" edit_insert="Y" edit_update="Y" edit_zoom="N" edit_copy="Y" valid_insert="Y" valid_update="Y" edit_round="N" />
  <Edit _uuid="8EWUq71rqdLHvyc3aGTPtg" name="code" label="M#12cn12代码" is_valid="Y" note="M#" disp_search="Y" disp_lov="Y" disp_display="Y" disp_insert="Y" disp_update="Y" disp_delete="Y" disp_print="Y" style_edit="editMax" data_name="CODE" edit_insert="Y" edit_update="Y" edit_zoom="N" edit_copy="Y" valid_insert="Y" valid_update="Y" />
  <Edit _uuid="IUS0m8PySdtIbZoHB1Qqmg" name="fullCode" label="M#12cn14代码全称" is_valid="Y" note="M#" disp_search="Y" disp_lov="Y" disp_display="Y" disp_insert="Y" disp_update="Y" disp_delete="Y" disp_print="Y" style_edit="editMax" data_name="FULL_CODE" edit_insert="Y" edit_update="Y" edit_zoom="N" edit_copy="Y" valid_insert="Y" valid_update="Y" />
  <Memo _uuid="fkoirJcfekqu3TiWehkGmw" name="includeHeads" label="M#12cn14包含列表" is_valid="Y" note="M#" disp_search="Y" disp_lov="Y" disp_display="Y" disp_insert="Y" disp_update="Y" disp_delete="Y" disp_print="Y" style_edit="memoMax" data_fetch="Y" data_name="INCLUDE_HEADS" edit_insert="Y" edit_update="Y" edit_zoom="N" edit_copy="Y" valid_insert="Y" valid_update="Y" edit_height="60" edit_overflow="N" />
  <Template _uuid="Zk6QbIa5P4F6CFOhiS7ohA" name="sourceTemplate" label="M#" is_valid="Y" note="M#" template_name="game.editor.entity.SourceTemplate" />
  <Template _uuid="UEONYmcSul7xIHGZQKoInA" name="noteTemplate" label="M#" is_valid="Y" note="M#" template_name="game.editor.entity.NoteTemplate" />
</WebForm>

