<?xml version="1.0" encoding="UTF-8"?>
<DataStore _uuid="pUbrBVKvcYl6yRb6OgZDiQ" name="game.template.task.trigger" label="M#12cn14任务触发" is_valid="Y" note="M#" access_insert="Y" access_update="Y" access_delete="Y" data_name="GM_TPL_TASK_TRIGGER" data_alias="GM_TPL_TSK_TRG" data_logic="GM_TPL_TASK_TRIGGER_DI" logic_insert="doInsert" logic_update="doUpdate" logic_delete="doDelete" parent_name="template.store" data_type="D">
  <FieldInteger _uuid="4UtQ2TBr2tTEEMjYJYaylQ" name="project_id" label="M#12cn14项目编号" is_valid="Y" note="M#" is_null="Y" is_store="Y" is_abstract="N" data_name="PROJECT_ID" data_alias="PRJ" data_refer="develop.project" />
  <FieldString _uuid="r0LJdMYjv4ggy5AArQ6psA" name="code" label="M#12cn12代码" is_valid="Y" note="M#" is_null="Y" is_store="Y" is_abstract="N" data_name="CODE" data_size="40" />
  <FieldInteger _uuid="xUBW7NpSQ764Sl1DddTOmQ" name="task_tid" label="M#12cn16任务模板编号" note="M#" is_store="Y" is_abstract="N" data_name="TASK_TID" data_alias="TSK" data_refer="game.template.task" />
  <FieldEnum _uuid="xUcjpQ7M[vC]pABxjPUkkw" name="mode_cd" label="M#12cn14触发方式" is_valid="Y" note="M#" is_null="Y" is_store="Y" is_abstract="N" data_name="MODE_CD" data_size="2" data_code="game.template.task.trigger" />
  <FieldString _uuid="kUXKRUjV983eOMvW43Ijjw" name="param1" label="M#12cn13参数1" is_valid="Y" note="M#" is_null="Y" is_store="Y" is_abstract="N" data_name="PARAM1" data_size="200" />
  <FieldString _uuid="]U7CvGoLb7mEJxu1CeLMmQ" name="param2" label="M#12cn13参数2" is_valid="Y" note="M#" is_null="Y" is_store="Y" is_abstract="N" data_name="PARAM2" data_size="200" />
  <FieldString _uuid="[0y]7mJ5AO3RqD]KnVgjnQ" name="param3" label="M#12cn13参数3" is_valid="Y" note="M#" is_null="Y" is_store="Y" is_abstract="N" data_name="PARAM3" data_size="200" />
  <FieldString _uuid="[ke0S[fEY1myN7[jSkrrhw" name="param4" label="M#12cn13参数4" is_valid="Y" note="M#" is_null="Y" is_store="Y" is_abstract="N" data_name="PARAM4" data_size="200" />
  <FieldString _uuid="cUV]KE4OCTXkpJui6Q6agw" name="param5" label="M#12cn13参数5" is_valid="Y" note="M#" is_null="Y" is_store="Y" is_abstract="N" data_name="PARAM5" data_size="200" />
  <FieldTemplate _uuid="c0Qe2siOEWidzW[xWwlStw" name="describe" label="M#12cn14描述模板" is_valid="Y" note="M#" template_name="template.describe" />
</DataStore>

