<?xml version="1.0" encoding="UTF-8"?>
<Root>
  <Context name="dataset.label">
    <jp />
    <zh>权限用户组关联用户</zh>
  </Context>
  <Context name="dataset.description">
    <jp />
    <zh />
  </Context>
  <Context name="field.group_id.label">
    <jp>Group Id</jp>
    <zh>Group Id</zh>
  </Context>
  <Context name="field.group_id.description">
    <jp />
    <zh />
  </Context>
  <Context name="field.user_id.label">
    <jp>User Id</jp>
    <zh>用户标识</zh>
  </Context>
  <Context name="field.user_id.description">
    <jp />
    <zh />
  </Context>
  <Context name="field.group_name.label">
    <zh>用户组</zh>
  </Context>
  <Context name="field.group_name.description">
    <zh />
  </Context>
</Root>

