<?xml version="1.0" encoding="utf-8"?>
<CodeList is_valid="Y" name="game.template.battle.event.action" label="战斗事件命令类型" data_name="GM_TPL_BATTLE_EVENT_ACT">
  <Code is_valid="Y" type="I" name="unknown" label="未知" data_name="Unknown" data_value="0" />
  <Code is_valid="Y" type="I" name="move" label="移动" data_name="Move" data_value="1" />
  <Code is_valid="Y" type="I" name="attack" label="攻击" data_name="Attack" data_value="2" />
  <Code is_valid="Y" type="I" name="bear" label="受击" data_name="Bear" data_value="3" />
  <Code is_valid="Y" type="I" name="death" label="死亡" data_name="Death" data_value="4" />
  <Code is_valid="Y" type="I" name="fly" label="打飞" data_name="Fly" data_value="5" />
  <Code is_valid="Y" type="I" name="magic" label="施法" data_name="Magic" data_value="6" />
  <Code is_valid="Y" type="I" name="rebirth" label="复活" data_name="Rebirth" data_value="7" />
  <Code is_valid="Y" type="I" name="add_entity" label="添加实体" data_name="AddEntity" data_value="8" />
  <Code is_valid="Y" type="I" name="remove_entity" label="删除实体" data_name="RemoveEntity" data_value="9" />
  <Code is_valid="Y" type="I" name="flee" label="逃跑" data_name="Flee" data_value="10" />
  <Code is_valid="Y" type="I" name="flee_fail" label="逃跑失败" data_name="FleeFail" data_value="11" />
  <Code is_valid="Y" type="I" name="dodge" label="躲闪" data_name="Dodge" data_value="12" />
  <Code is_valid="Y" type="I" name="show_word" label="显示文字" data_name="ShowWord" data_value="13" />
  <Code is_valid="Y" type="I" name="show_message" label="提示信息" data_name="ShowMessage" data_value="14" />
  <Code is_valid="Y" type="I" name="chat_content" label="聊天内容" data_name="ChatContent" data_value="15" />
</CodeList>