<?xml version="1.0" encoding="UTF-8"?>
<DataStore _uuid="oUBvm2aAJ0q[UkFh0IcYkA" name="person.user" label="M#12cn14用户信息" is_valid="Y" note="M#" data_name="PM_USER" data_logic="PM_USER_DI" logic_insert="doInsert" logic_update="doUpdate" logic_delete="doDelete" parent_name="template.store" data_type="D">
  <FieldBoolean _uuid="oEpFXD4RuXhdmuK40OHHnA" name="is_valid" label="M#12cn13有效性" is_valid="Y" note="M#" is_null="Y" is_store="Y" is_abstract="N" data_name="IS_VALID" />
  <FieldInteger _uuid="vkGdtYE4pD76dtPKdnbCqA" name="type_id" label="M#12cn14用户类型" is_valid="Y" note="M#12cn218可设定的类型有公司员工/面试者/其它" is_null="Y" is_store="Y" is_abstract="N" data_name="TYPE_ID" data_refer="person.user.type" />
  <FieldEnum _uuid="jUZnGuyAq78bN]KQGIqRoA" name="status_cd" label="M#12cn14状态类型" is_valid="Y" note="M#12cn224保留/激活/锁定\n只有激活状态的用户可以登录系统" is_null="Y" is_store="Y" is_abstract="N" data_name="STATUS_CD" data_type="Enum" data_size="1" data_code="person.user.status" data_default="'R'" />
  <FieldEnum _uuid="c05W]hrAPIJBof7ill5TiQ" name="login_type" label="M#12cn14登录类型" is_valid="Y" note="M#12cn19默认是密码直接认证" is_null="Y" is_store="Y" is_abstract="N" data_name="LOGIN_TYPE" data_size="1" data_code="person.user.passport" />
  <FieldString _uuid="D0GGnoIFzQ8c9jhwoYu5og" name="login_passport" label="M#12cn14登录帐号" is_valid="Y" note="M#" is_null="Y" is_unique="Y" is_store="Y" is_abstract="N" data_name="LOGIN_PASSPORT" data_alias="LOGIN_PS" data_type="String" data_size="40" />
  <FieldString _uuid="Y0Tu]ksIQT5DXCQrviDGlg" name="login_password" label="M#12cn14登录密码" is_valid="Y" note="M#" is_null="Y" is_store="Y" is_abstract="N" data_name="LOGIN_PASSWORD" data_type="String" data_size="40" />
  <FieldString _uuid="2k5G0MM1tviFuKKEQ1vcvQ" name="login_code" label="M#12cn14登录代码" is_valid="Y" note="M#" is_null="Y" is_store="Y" is_abstract="N" data_name="LOGIN_CODE" data_size="80" />
  <FieldString _uuid="EkaHqE2HyJACDTq1wxjrlg" name="name_first" label="M#12cn14拼音姓氏" is_valid="Y" note="M#" is_null="Y" is_store="Y" is_abstract="N" data_name="NAME" data_type="String" data_size="40" />
  <FieldString _uuid="60TLUKcAtnqA[GjwCpVViA" name="name_last" label="M#12cn14拼音名字" is_valid="Y" note="M#" is_null="Y" is_store="Y" is_abstract="N" data_name="NAME_LAST" data_type="String" data_size="40" />
  <FieldChar _uuid="Ok3GjMQrrBm2]jz680mKnw" name="short_name" label="M#12cn14英文简称" is_valid="Y" note="M#" is_null="Y" is_store="Y" is_abstract="N" data_name="SHORT_NAME" data_size="20" />
  <FieldContent _uuid="2EFLjGuubdRENuucSh0mrA" name="label_first" label="M#12cn14中文姓氏" is_valid="Y" note="M#" is_null="Y" is_store="Y" data_name="LABEL" data_type="Content" />
  <FieldContent _uuid="0EDrJlgNytD]TMSY0lh1vQ" name="label_last" label="M#12cn14中文名字" is_valid="Y" note="M#" is_null="Y" is_store="Y" data_name="LABEL_LAST" data_type="Content" />
  <FieldEnum _uuid="mkw9g34bR8ZMSvw60xfgtg" name="label_privacy_cd" label="M#12cn16名称隐私设置" is_valid="Y" note="M#" is_null="Y" is_store="Y" is_abstract="N" data_name="LABEL_PRIVACY_CD" data_alias="PRIVACY_LAB" data_type="Enum" data_size="1" data_code="person.user.privacy" />
  <FieldBoolean _uuid="sENxtufDwUCVPZTHspETjg" name="label_disp_able" label="M#12cn16名称显示可能" is_valid="Y" note="M#12cn19不可时，只显示别称" is_null="Y" is_store="Y" data_name="LABEL_DISP_ABLE" data_type="Boolean" />
  <FieldString _uuid="rkVW]MNklKgncqi70dEOjA" name="alias" label="M#12cn12别称" is_valid="Y" note="M#12cn18隐藏真实名称用的" is_null="Y" is_store="Y" data_name="ALIAS" data_type="String" data_size="40" />
  <FieldInteger _uuid="1kxh3jYVBaW9Y3bmDjNXpA" name="nationality_id" label="M#12cn12民族" is_valid="Y" note="M#" is_null="Y" is_store="Y" is_abstract="N" data_name="NATIONALITY_ID" data_alias="NATIONAL" data_refer="common.nationality" />
  <FieldInteger _uuid="K0hg1r8sUdl]WWYanDl[oQ" name="height" label="M#12cn12身高" is_valid="Y" note="M#12cn15单位:厘米" is_null="Y" is_store="Y" is_abstract="N" data_name="HEIGHT" />
  <FieldInteger _uuid="]0YQ52TxBXorp98F[[dVoQ" name="weight" label="M#12cn12体重" is_valid="Y" note="M#12cn15单位：千克" is_null="Y" is_store="Y" is_abstract="N" data_name="WEIGHT" />
  <FieldEnum _uuid="]kHmq9hUfk1UDD7Ha5k3ow" name="blood_cd" label="M#12cn12血型" is_valid="Y" note="M#12cn221A=A\nB=B\nC=AB\nO=O\nT=其它" is_null="Y" is_store="Y" is_abstract="N" data_name="BLOOD_CD" data_type="Enum" data_size="1" data_code="person.user.blood" />
  <FieldEnum _uuid="C0xcELYsqJjHIyENOFCqpg" name="blood_privacy_cd" label="M#12cn16血型隐私设置" is_valid="Y" note="M#" is_null="Y" is_store="Y" is_abstract="N" data_name="BLOOD_PRIVACY_CD" data_alias="PRIVACY_BOL" data_type="Enum" data_size="1" data_code="person.user.privacy" />
  <FieldBoolean _uuid="SkB6x1Tiu3y[0RXg7Twdpg" name="blood_disp_able" label="M#12cn16血型显示可能" is_valid="Y" note="M#" is_null="Y" is_store="Y" data_name="BLOOD_DISP_ABLE" data_type="Boolean" />
  <FieldChar _uuid="XEHfdgA79rr1Z0t8304DvA" name="id_number" label="M#12cn13身份证" is_valid="Y" note="M#" is_null="Y" is_unique="Y" is_store="Y" is_abstract="N" data_name="ID_NUMBER" data_type="Char" data_size="18" />
  <FieldChar _uuid="0UNnvwCkqVcQ[EHV6klJuQ" name="passport" label="M#12cn12护照" is_valid="Y" note="M#" is_null="Y" is_unique="Y" is_store="Y" is_abstract="N" data_name="PASSPORT" data_type="Char" data_size="18" />
  <FieldEnum _uuid="SUWcnNKRLchGl]NRIgsigQ" name="gender_cd" label="M#12cn12性别" is_valid="Y" note="M#" is_null="Y" is_store="Y" is_abstract="N" data_name="GENDER_CD" data_type="Enum" data_size="1" data_code="person.user.sex" />
  <FieldEnum _uuid="dEGHq7HPR3emVe0jrM1rsQ" name="gender_privacy_cd" label="M#12cn16性别隐私设置" is_valid="Y" note="M#" is_null="Y" is_store="Y" is_abstract="N" data_name="GENDER_PRIVACY_CD" data_alias="PRIVACY_SEX" data_type="Enum" data_size="1" data_code="person.user.privacy" />
  <FieldBoolean _uuid="MEEFbmzCCZ8RHsyB28Aajg" name="gender_disp_able" label="M#12cn16性别显示可能" is_valid="Y" note="M#" is_null="Y" is_store="Y" data_name="GENDER_DISP_ABLE" data_type="Boolean" />
  <FieldDate _uuid="aE9Je]SUMTIrf89YFwMfrQ" name="birthday" label="M#12cn12生日" is_valid="Y" note="M#" is_null="Y" is_store="Y" is_abstract="N" data_name="BIRTHDAY" data_type="Date" />
  <FieldEnum _uuid="I0tMSDOo]H4XcocPwhg0pQ" name="political_cd" label="M#12cn14政治面貌" is_valid="Y" note="M#12cn219D=党员\nT=团员\nQ=群众\nO=其他" is_null="Y" is_store="Y" is_abstract="N" data_name="POLITICAL_CD" data_type="Enum" data_size="1" data_code="person.user.political" />
  <FieldEnum _uuid="l0D9JIXNtCJqwaiawo5lqQ" name="education_cd" label="M#12cn14最高学历" is_valid="Y" note="M#12cn3117P=Postdoctoral(博士后)\nD=Doctoral(博士)\nM=Magister(硕士)\nU=Undergraduate(本科)\nA=Associate(大专)\nH=HighSchool(高中)\nO=Other(其他)   " is_null="Y" is_store="Y" is_abstract="N" data_name="EDUCATION_CD" data_type="Enum" data_size="1" data_code="person.user.education.level" />
  <FieldInteger _uuid="30rA4iSQzuwzQTWLaSRYng" name="birth_province_id" label="M#12cn16籍贯省份标识" is_valid="Y" note="M#" is_null="Y" is_store="Y" is_abstract="N" data_name="BIRTH_PROVINCE_ID" data_refer="common.province" />
  <FieldString _uuid="PUdsZQ2vIU7WahjJuq6Cow" name="birth_place" label="M#12cn12籍贯" is_valid="Y" note="M#" is_null="Y" is_store="Y" is_abstract="N" data_name="BIRTH_PLACE" data_type="String" data_size="80" />
  <FieldEnum _uuid="CEdpTBcvst1FfDMoWytyhA" name="domicile_cd" label="M#12cn14户口性质" is_valid="Y" note="M#12cn229R=Residents(居民)\nF=Farmer(非居民)" is_null="Y" is_store="Y" is_abstract="N" data_name="DOMICILE_CD" data_size="1" data_code="person.user.domicile" />
  <FieldInteger _uuid="pUwO10Jj7FmPOUggCG9OjQ" name="domicile_province_id" label="M#12cn14户口省份" is_valid="Y" note="M#" is_null="Y" is_store="Y" is_abstract="N" data_name="DOMICILE_PROVINCE_ID" data_refer="common.province" />
  <FieldString _uuid="JE9d2ZbJ9JAjfdiLlCp4iQ" name="domicile_place" label="M#12cn15户口所在地" is_valid="Y" note="M#" is_null="Y" is_store="Y" is_abstract="N" data_name="DOMICILE_PLACE" data_size="80" />
  <FieldInteger _uuid="h0g8dMLf6duFxF8MnCYXmg" name="address_province_id" label="M#12cn16住址省份标识" is_valid="Y" note="M#" is_null="Y" is_store="Y" is_abstract="N" data_name="ADDRESS_PROVINCE_ID" data_refer="common.province" />
  <FieldInteger _uuid="kU574ImlxoFNMj4HqwfLqg" name="address_postcode" label="M#12cn12邮编" is_valid="Y" note="M#" is_null="Y" is_store="Y" is_abstract="N" data_name="ADDRESS_POSTCODE" data_size="6" />
  <FieldString _uuid="ekpLFtJX9Q4NjPu[iZbSqw" name="address_place" label="M#12cn12住址" is_valid="Y" note="M#" is_null="Y" is_store="Y" is_abstract="N" data_name="ADDRESS_PLACE" data_size="80" />
  <FieldInteger _uuid="wUsPFXt7UGVFe[]oP5VOlQ" name="family_province_id" label="M#12cn16家庭住址省份" is_valid="Y" note="M#" is_null="Y" is_store="Y" is_abstract="N" data_name="FAMILY_PROVINCE_ID" data_refer="common.province" />
  <FieldInteger _uuid="SkQj2eVwoMkwTQs]9]8yjQ" name="family_postcode" label="M#12cn14家庭邮编" is_valid="Y" note="M#" is_null="Y" is_store="Y" is_abstract="N" data_name="FAMILY_POSTCODE" data_size="6" />
  <FieldString _uuid="1URd4MEixiQiNGvMckamtg" name="family_address" label="M#12cn14家庭住址" is_valid="Y" note="M#" is_null="Y" is_store="Y" is_abstract="N" data_name="FAMILY_ADDRESS" data_size="80" />
  <FieldInteger _uuid="E05zntULWLGauqaq8hQ2ow" name="record_province_id" label="M#12cn16档案省份标识" is_valid="Y" note="M#" is_null="Y" is_store="Y" is_abstract="N" data_name="RECORD_PROVINCE_ID" />
  <FieldString _uuid="Ikpk]rmmMe4O1Ux7wyleuQ" name="record_place" label="M#12cn15档案所在地" is_valid="Y" note="M#" is_null="Y" is_store="Y" is_abstract="N" data_name="RECORD_PLACE" data_size="80" />
  <FieldEnum _uuid="Qk89mmyC8dfloYFprr8[ow" name="birthday_privacy_cd" label="M#12cn16生日隐私设置" is_valid="Y" note="M#" is_null="Y" is_store="Y" is_abstract="N" data_name="BIRTHDAY_PRIVACY_CD" data_alias="PRIVACY_BRD" data_type="Enum" data_size="1" data_code="person.user.privacy" />
  <FieldBoolean _uuid="[UiXbYfKX0Qr5LpUHxQGng" name="birthday_disp_able" label="M#12cn16生日显示可能" is_valid="Y" note="M#" is_null="Y" is_store="Y" is_abstract="N" data_name="BIRTHDAY_DISP_ABLE" data_type="Boolean" />
  <FieldEnum _uuid="p0nnwQW0tE3op7jISwkOvg" name="marriage_cd" label="M#12cn12婚姻" is_valid="Y" note="M#" is_null="Y" is_store="Y" is_abstract="N" data_name="MARRIAGE_CD" data_type="Enum" data_size="1" data_code="person.user.marriage" />
  <FieldEnum _uuid="k0At7PO2cVCIPyHFyDyYsA" name="marriage_privacy_cd" label="M#12cn16婚姻隐私设置" is_valid="Y" note="M#" is_null="Y" is_store="Y" is_abstract="N" data_name="MARRIAGE_PRIVACY_CD" data_alias="PRIVACY_WED" data_type="Enum" data_size="1" data_code="person.user.privacy" />
  <FieldBoolean _uuid="5E]TFxbNj6Apq1nIs4g[kQ" name="marriage_disp_able" label="M#12cn16婚姻显示可能" is_valid="Y" note="M#" is_null="Y" is_store="Y" data_name="MARRIAGE_DISP_ABLE" data_type="Boolean" />
  <FieldBoolean _uuid="wEnKQ89SO9Y4UtdGsU0[uQ" name="has_children" label="M#12cn15是否有子女" is_valid="Y" note="M#" is_null="Y" is_store="Y" is_abstract="Y" data_name="HAS_CHILDREN" />
  <FieldEnum _uuid="NEyd9UJbq4X5upffH5]zsA" name="astro_cd" label="M#12cn12星座" is_valid="Y" note="M#" is_null="Y" is_store="Y" is_abstract="N" data_name="ASTRO_CD" data_type="Enum" data_size="1" data_code="person.user.constellation" />
  <FieldEnum _uuid="jkd479[eOoJMirJwuNJHtg" name="astro_privacy_cd" label="M#12cn16星座隐私设置" is_valid="Y" note="M#" is_null="Y" is_store="Y" is_abstract="N" data_name="ASTRO_PRIVACY_CD" data_alias="PRIVACY_AST" data_type="Enum" data_size="1" data_code="person.user.privacy" />
  <FieldBoolean _uuid="0ErMN0K7PCwCMjvQt78tjA" name="astro_disp_able" label="M#12cn16星座显示可能" is_valid="Y" note="M#" is_null="Y" is_store="Y" data_name="ASTRO_DISP_ABLE" data_type="Boolean" />
  <FieldEnum _uuid="ukFpqGN[8GmTQebt[yOSrw" name="body_cd" label="M#12cn12体型" is_valid="Y" note="M#" is_null="Y" is_store="Y" is_abstract="N" data_name="BODY_CD" data_type="Enum" data_size="1" data_code="person.user.bodily.form" />
  <FieldEnum _uuid="GEjyk8mFu6Ot3AoIP44ehA" name="body_privacy_cd" label="M#12cn16体型隐私设置" is_valid="Y" note="M#" is_null="Y" is_store="Y" is_abstract="N" data_name="BODY_PRIVACY_CD" data_alias="PRIVACY_BOD" data_type="Enum" data_size="1" data_code="person.user.privacy" />
  <FieldBoolean _uuid="q0jZpX6izFKS0FcnhPXnnQ" name="body_disp_able" label="M#12cn16体型显示可能" is_valid="Y" note="M#" is_null="Y" is_store="Y" data_name="BODY_DISP_ABLE" data_type="Boolean" />
  <FieldBoolean _uuid="7kczLMiQbEL2X5O7HVdMqw" name="has_icon" label="M#12cn15是否有图标" is_valid="Y" note="M#" is_null="Y" is_store="Y" data_name="HAS_ICON" data_type="Boolean" />
  <FieldBoolean _uuid="ckscgPpIwxz88ERFu[N4qQ" name="has_picture" label="M#12cn15是否有图片" is_valid="Y" note="M#" is_null="Y" is_store="Y" data_name="HAS_PICTURE" data_type="Boolean" />
  <FieldBoolean _uuid="3k75b69jpyrAtKQfbvEJqQ" name="has_criminal_record" label="M#12cn17是否有犯罪记录" is_valid="Y" note="M#" is_null="Y" is_store="Y" is_abstract="Y" data_name="HAS_CRIMINAL_RECORD" />
  <FieldString _uuid="K0Nk1t1vwHWNUGjhEl6BpA" name="interest" label="M#12cn12爱好" is_valid="Y" note="M#" is_null="Y" is_store="Y" is_abstract="N" data_name="INTEREST" data_size="80" />
  <FieldString _uuid="yEHDYvFbDtIi9h6waHHhmA" name="specialty " label="M#12cn12特长" is_valid="Y" note="M#12cn210由单选框选择多个特长" is_null="Y" is_store="Y" is_abstract="N" data_name="SPECIALTY" data_size="80" />
  <FieldDate _uuid="iEkZJ7OQuVB3QiDtS3lggA" name="first_career_date" label="M#12cn19第一次参加工作时间" is_valid="Y" note="M#" is_null="Y" is_store="Y" is_abstract="N" data_name="FIRST_CAREER_DATE" />
  <FieldFloat _uuid="pUbp8q2OnviI[Pa60JVqqA" name="work_age" label="M#12cn12工龄" is_valid="Y" note="M#" is_null="Y" is_store="Y" is_abstract="N" data_name="WORK_AGE" />
  <FieldDate _uuid="m0I3pXxzY7[Io[MPpo3Ekw" name="create_date" label="M#12cn14创建时间" is_valid="Y" note="M#" is_null="Y" is_store="Y" is_abstract="N" data_name="CREATE_DATE" data_type="Date" data_default="SYSDATE" />
  <FieldContent _uuid="LUmWCy84omDdm9ngAHo[vg" name="note" label="M#12cn12备注" is_valid="Y" note="M#" is_null="Y" is_store="Y" data_name="NOTE" data_type="Content" />
</DataStore>

