<?xml version="1.0" encoding="UTF-8"?>
<WebForm _uuid="NUpEBgH9L[UHHUNJSHj]uQ" name="design.webform.ChartForm" label="M#12cn14图表表单" is_valid="Y" note="M#" disp_fetch="Y" disp_search="Y" disp_lov="Y" disp_zoom="Y" disp_insert="Y" disp_update="Y" disp_delete="Y" disp_print="Y" style_refer="design.webform.ControlStyle" edit_copy="Y" edit_fetch="Y" edit_search="Y" edit_picker="Y" edit_zoom="Y" edit_print="Y" edit_action="Y" edit_insert="Y" edit_update="Y" edit_delete="Y" disp_toolbar="Y">
  <Template _uuid="c0oAwkT3sx1p9BEGk7IBsQ" name="basicTemplate" label="M#" is_valid="Y" note="M#" template_name="design.webform.BasicTemplate" />
  <Template _uuid="]U4[UoI[siBQbbdJT]0Rpw" name="labelTemplate" label="M#" is_valid="Y" note="M#" template_name="design.webform.LabelTemplate" />
  <Template _uuid="vU8jdgRLIBI1FULUIy2TvA" name="displayTemplate" label="M#" is_valid="Y" note="M#" template_name="design.webform.DisplayTemplate" />
  <Template _uuid="4UdZ4PAq5TI57f4WP7Algg" name="dataTemplate" label="M#" is_valid="Y" note="M#" template_name="design.webform.DataTemplate" />
  <Edit _uuid="wUA1ZzEcE39lUdc9HMcEkQ" name="dataService" label="M#12cn14数据服务" is_valid="Y" note="M#" disp_search="Y" disp_lov="Y" disp_display="Y" disp_insert="Y" disp_update="Y" disp_delete="Y" disp_print="Y" nowrap="Y" style_edit="editMax" data_fetch="Y" data_name="DATA_SERVICE" edit_insert="Y" edit_update="Y" valid_insert="Y" valid_update="Y" />
  <Select _uuid="ukBgEqlC5f0vtJiSYspShA" name="flashType" label="M#12cn17flash类型" is_valid="Y" note="M#" disp_search="Y" disp_lov="Y" disp_display="Y" disp_insert="Y" disp_update="Y" disp_delete="Y" disp_print="Y" data_fetch="Y" data_name="FLASH_TYPE" edit_insert="Y" edit_update="Y" edit_zoom="N" edit_copy="Y" valid_insert="Y" valid_update="Y" valid_require="Y" edit_refer="design.chart.FlashType" edit_dynamic="N" />
  <Template _uuid="yElFEkWSP[lkv8DcyDoyvg" name="editTemplate" label="M#" is_valid="Y" note="M#" template_name="design.webform.EditTemplate" />
  <Template _uuid="9kHbKGPew2qFOMDXiUGRjg" name="noteTemplate" label="M#" is_valid="Y" note="M#" template_name="design.webform.NoteTemplate" />
</WebForm>

