<?xml version="1.0" encoding="UTF-8"?>
<WebForm _uuid="SUXIm4JO]46GgVfJPyvvpQ" _type="WebForm" name="design.webform.MenuButtonForm" label="M#12cn18工具栏-命令按键" is_valid="Y" note="M#" style_refer="design.webform.ControlStyle" edit_insert="Y" edit_update="Y" action="/system/design/webform/WebForm.wa?type=field">
  <DataAction _uuid="x0Rs4iE]EfNgNgxJyAVslA" _type="DataAction" name="insertAction" label="M#12cn14新建命令" is_valid="Y" note="M#" service="insert@design.webform" />
  <DataAction _uuid="uklTppm]NQ1e[]m2aKMzpg" _type="DataAction" name="updateAction" label="M#12cn14保存命令" is_valid="Y" note="M#" service="update@design.webform" />
  <DataAction _uuid="3kobVM4LC3s7fVfvuyUCoA" _type="DataAction" name="deleteAction" label="M#12cn14删除命令" is_valid="Y" note="M#" service="delete@design.webform" />
  <ToolBar _uuid="zECEGykza4WE75eAQvMZhQ" _type="ToolBar" name="toolBar" label="M#12cn13工具栏" is_valid="Y" note="M#" disp_search="Y" disp_picker="Y" disp_list="Y" disp_insert="Y" disp_update="Y" disp_delete="Y" width="100%" height="24">
    <ToolButton _uuid="RUavtd0QPq2HKUGxOoQuvw" _type="ToolButton" name="updateButton" label="M#12cn12保存" is_valid="Y" note="M#" disp_search="Y" disp_picker="Y" disp_list="Y" disp_insert="Y" disp_update="Y" disp_delete="Y" icon="#tools.save" icon_disable="#tools.saveDisable" hotkey="F8" action="doSave()" />
    <ToolButton _uuid="T02NVrhoRh1xdPCdELaggw" _type="ToolButton" name="deleteButton" label="M#12cn12删除" is_valid="Y" note="M#" disp_search="Y" disp_picker="Y" disp_list="Y" disp_insert="Y" disp_update="Y" disp_delete="Y" icon="#tools.delete" icon_disable="#tools.deleteDisable" hotkey="F6" action="doDelete()" />
  </ToolBar>
  <Select _uuid="Z0Q7froaa6XI6cHn0KnJqw" _type="Select" name="type" label="M#12cn14控件类型" is_valid="Y" note="M#" disp_fetch="N" disp_search="Y" disp_picker="Y" disp_lov="N" disp_zoom="N" disp_insert="Y" disp_update="Y" disp_delete="Y" nowrap="Y" style_edit="selectMax" data_name="_TYPE" data_default="ToolButton" valid_update="Y" valid_require="N" edit_refer="design.webform.ComponentType" edit_check="N" />
  <Check _uuid="F0Lf9Jz42AqD]jBW9fQasw" _type="Check" name="isValid" label="M#12cn13有效性" is_valid="Y" note="M#" disp_search="Y" disp_list="Y" disp_insert="Y" disp_update="Y" disp_delete="Y" data_name="IS_VALID" data_default="Y" edit_insert="Y" edit_update="Y" valid_insert="Y" valid_update="Y" label_position="left" />
  <Edit _uuid="NU6E4TIR2hijNamb2RJQpw" _type="Edit" name="name" label="M#12cn12名称" is_valid="Y" note="M#" disp_search="Y" disp_picker="Y" disp_list="Y" disp_insert="Y" disp_update="Y" disp_delete="Y" nowrap="Y" data_name="NAME" edit_insert="Y" edit_update="Y" valid_insert="Y" valid_update="Y" valid_require="Y" />
  <Edit _uuid="zkP2xfUa0G2jTwbTMugZhg" _type="Edit" name="hotkey" label="M#12cn12热键" is_valid="Y" note="M#" disp_search="Y" disp_picker="Y" disp_list="Y" disp_insert="Y" disp_update="Y" disp_delete="Y" style_refer="editNarrow" data_name="HOTKEY" edit_insert="Y" edit_update="Y" valid_insert="Y" valid_update="Y" />
  <Edit _uuid="CEpydAB3JvvEzToHIr1jsw" _type="Edit" name="label" label="M#12cn12标签" is_valid="Y" note="M#" disp_search="Y" disp_picker="Y" disp_list="Y" disp_insert="Y" disp_update="Y" disp_delete="Y" style_refer="editWide" data_name="LABEL" edit_insert="Y" edit_update="Y" valid_insert="Y" valid_update="Y" valid_require="Y" />
  <Check _uuid="Mk2Cx6YbTkWICSf2VRApuA" _type="Check" name="dispList" label="M#12cn12列表" is_valid="Y" note="M#" disp_search="Y" disp_picker="Y" disp_insert="Y" disp_update="Y" disp_delete="Y" nowrap="Y" style_refer="checkNarrow" data_name="DISP_LIST" data_default="Y" edit_insert="Y" edit_update="Y" valid_insert="Y" valid_update="Y" />
  <Check _uuid="p0qSXto10lcv9ODAumPGig" _type="Check" name="dispInsert" label="M#12cn12新建" is_valid="Y" note="M#" disp_search="Y" disp_picker="Y" disp_list="Y" disp_insert="Y" disp_update="Y" disp_delete="Y" style_refer="checkNarrow" data_name="DISP_INSERT" data_default="Y" edit_insert="Y" edit_update="Y" valid_insert="Y" valid_update="Y" />
  <Check _uuid="s0MgKd2283lw3Sp5OQ8Tiw" _type="Check" name="dispUpdate" label="M#12cn12更新" is_valid="Y" note="M#" disp_search="Y" disp_picker="Y" disp_list="Y" disp_insert="Y" disp_update="Y" disp_delete="Y" nowrap="Y" style_refer="checkNarrow" data_name="DISP_UPDATE" data_default="Y" edit_insert="Y" edit_update="Y" valid_insert="Y" valid_update="Y" />
  <Check _uuid="ekPswaoO6[xugW37Ifaupg" _type="Check" name="dispDelete" label="M#12cn12删除" is_valid="Y" note="M#" disp_search="Y" disp_picker="Y" disp_list="Y" disp_insert="Y" disp_update="Y" disp_delete="Y" style_refer="checkNarrow" data_name="DISP_DELETE" data_default="Y" edit_insert="Y" edit_update="Y" valid_insert="Y" valid_update="Y" />
  <IconPicker _uuid="sEfz78gAv485sMhsoqRHkg" _type="IconPicker" name="icon" label="M#12cn12图标" is_valid="Y" note="M#" disp_search="Y" disp_insert="Y" disp_update="Y" disp_delete="Y" style_refer="iconPickerWide" data_name="ICON" edit_insert="Y" edit_update="Y" valid_insert="Y" valid_update="Y" />
  <IconPicker _uuid="gE4NUygKUeNIZo[m0Bl]pg" _type="IconPicker" name="iconDisable" label="M#12cn14禁止图标" is_valid="Y" note="M#" disp_search="Y" disp_list="Y" disp_insert="Y" disp_update="Y" disp_delete="Y" style_refer="iconPickerWide" data_name="ICON_DISABLE" edit_insert="Y" edit_update="Y" valid_insert="Y" valid_update="Y" label_width="80" />
  <Edit _uuid="0kiKuFKaK0QY]9is78EHtQ" _type="Edit" name="action" label="M#12cn12命令" is_valid="Y" note="M#" disp_search="Y" disp_picker="Y" disp_list="Y" disp_insert="Y" disp_update="Y" disp_delete="Y" style_refer="editWide" data_name="ACTION" edit_insert="Y" edit_update="Y" valid_insert="Y" valid_update="Y" />
  <Edit _uuid="gEc9SzYWLjYgm[kciD61mA" _type="Edit" name="page" label="M#12cn14转向页面" is_valid="Y" note="M#" disp_search="Y" disp_picker="Y" disp_list="Y" disp_insert="Y" disp_update="Y" disp_delete="Y" style_refer="editWide" data_name="PAGE" edit_insert="Y" edit_update="Y" valid_insert="Y" valid_update="Y" />
  <Memo _uuid="xUW[1r9lWdOAJP5RADiDqw" _type="Memo" name="attributes" label="M#12cn14属性内容" is_valid="Y" note="M#" disp_search="Y" disp_picker="Y" disp_list="Y" disp_insert="Y" disp_update="Y" disp_delete="Y" data_name="ATTRIBUTES" edit_insert="Y" edit_update="Y" valid_insert="Y" valid_update="Y" />
  <Memo _uuid="d0l1vZY]UsIQGGNNkN1mnw" _type="Memo" name="note" label="M#12cn14描述信息" is_valid="Y" note="M#" disp_search="Y" disp_picker="Y" disp_list="Y" disp_insert="Y" disp_update="Y" disp_delete="Y" data_name="NOTE" edit_insert="Y" edit_update="Y" valid_insert="Y" valid_update="Y" />
</WebForm>

