<?xml version="1.0" encoding="UTF-8"?>
<CodeList _uuid="9U5FWcEabFX3uJ8N[K1rqQ" name="person.recruit.job.require.specialty" label="M#12cn12专业" is_valid="Y" note="M#" data_name="PM_RECRUIT_JOB_REQ_SPT">
  <Code _uuid="c07uXNkQpIbxy2CWcz66oA" name="computerSpecialty" label="M#12cn15计算机专业" is_valid="Y" note="M#" type="I" data_name="ComputerSpecialty" data_value="C" />
  <Code _uuid="u0mg[YtoT01rXsl8wsFbnQ" name="communicationServices" label="M#12cn210电子.电器.通信技术" is_valid="Y" note="M#" type="I" data_name="CommunicationServices" data_value="I" />
  <Code _uuid="r06mCL]uJzzQkf8JpwK4uw" name="market" label="M#12cn13销售类" is_valid="Y" note="M#" type="I" data_name="Market" data_value="K" />
  <Code _uuid="zEEf8AeuLeamZ6AJDVF1ug" name="financialStatistics" label="M#12cn18财务.审计.统计" is_valid="Y" note="M#" type="I" data_name="FinancialStatistics" data_value="A" />
  <Code _uuid="K0TAhLWm[1GU2J3V1hMCiw" name="medium" label="M#12cn18市场.公关.媒介" is_valid="Y" note="M#" type="I" data_name="Medium" data_value="D" />
  <Code _uuid="nUHpXW3HyuOliim0L][irQ" name="humanResource" label="M#12cn15人力资源类" is_valid="Y" note="M#" type="I" data_name="HumanResource" data_value="H" />
  <Code _uuid="l0v6UrZY]Lm1hriDCMM4tQ" name="inaugurate" label="M#12cn19美术.设计.创业类" is_valid="Y" note="M#" type="I" data_name="Inaugurate" data_value="N" />
  <Code _uuid="90jtr5MrFBdIOMQhOzvpgQ" name="finance" label="M#12cn220金融类(银行 .基金.证券.期货.投资)" is_valid="Y" note="M#" type="I" data_name="Finance" data_value="F" />
  <Code _uuid="R0yXjI6I7ecRZJZBCI]LqA" name="student" label="M#12cn14在校学生" is_valid="Y" note="M#" type="I" data_name="Student" data_value="S" />
  <Code _uuid="X0Zymer808LxUVYDNsMPmw" name="trade" label="M#12cn211贸易.物流.采购.运输" is_valid="Y" note="M#" type="I" data_name="Trade" data_value="T" />
  <Code _uuid="SE7ZU6PjedofUsBu5ZCWrA" name="projectManger" label="M#12cn15项目管理类" is_valid="Y" note="M#" type="I" data_name="ProjectManger" data_value="P" />
  <Code _uuid="yk4Vk4B[Q4x5ASiw9uuKgw" name="law" label="M#12cn13法律类" is_valid="Y" note="M#" type="I" data_name="Law" data_value="L" />
  <Code _uuid="CUJczjrmx[iD1sNQJym]tw" name="other" label="M#12cn13其他类" is_valid="Y" note="M#" type="I" data_name="Other" data_value="O" />
</CodeList>

